uconn/__init__.py
udb/__init__.py
udb/db_postgresql.py
udb/db_sqlite.py
ufile/__init__.py
uthread/__init__.py
utime/__init__.py
utools/__init__.py
nost_util_tools-1.0.0.dist-info/METADATA
nost_util_tools-1.0.0.dist-info/WHEEL
nost_util_tools-1.0.0.dist-info/top_level.txt
nost_util_tools-1.0.0.dist-info/RECORD
