Metadata-Version: 2.1
Name: nost-util-tools
Version: 1.0.0
Summary: This is a collection of tools that includes encapsulations of some commonly used utilities such as file and folder operations, common database operations, image processing, and network connectivity.
Home-page: https://gitee.com/nostmabole/py_util_tools
Author: Arthur Nostmabole Zhang
Author-email: nostmabole@sina.com
License: Apache License 2.0
Classifier: Programming Language :: Python :: 3.9
Classifier: Programming Language :: Python :: 3.10
Classifier: Programming Language :: Python :: 3.11
Classifier: License :: OSI Approved :: MIT License
Classifier: Operating System :: OS Independent
Requires-Dist: sqlalchemy ~=2.0.22
